morningstar/__init__.py
morningstar/config.py
morningstar/morningstar_client.py
morningstar/on_demand_client.py
morningstar/models/__init__.py
morningstar/models/instrument.py
morningstar/models/ms_response.py
morningstar/models/ms_result.py
morningstar/models/rips.py
morningstar/models/ts_response.py
morningstar/models/ts_result.py
morningstar/provider/__init__.py
morningstar/provider/morningstar.py
morningstar/provider/on_demand.py
morningstar/provider/provider.py
morningstar/spec/__init__.py
morningstar/spec/on_demand_spec.py
morningstar/spec/security_type_spec.py
morningstar/spec/web_service_spec.py
tests/__init__.py
tests/morningstar_client_mock.py
tests/morningstar_client_test.py
tests/morningstar_mock.py
tests/morningstar_test.py
tests/spec/__init__.py
tests/spec/security_type_spec_test.py
morningstar-0.3.1.dist-info/LICENSE
morningstar-0.3.1.dist-info/METADATA
morningstar-0.3.1.dist-info/WHEEL
morningstar-0.3.1.dist-info/top_level.txt
morningstar-0.3.1.dist-info/RECORD
