Metadata-Version: 2.1
Name: morningstar
Version: 0.3.1
Summary: Morningstar API Client
Home-page: https://github.com/aaaccell/morningstar
Author: Marc Juchli
Author-email: marcjuchli@aaaccell.ch
License: MIT
Platform: UNKNOWN
Classifier: Programming Language :: Python :: 3
Classifier: License :: OSI Approved :: MIT License
Classifier: Operating System :: OS Independent
